hdfuse/__init__.py
hdfuse/hdfuse.py
hdfuse-1.0.2.dist-info/LICENSE
hdfuse-1.0.2.dist-info/METADATA
hdfuse-1.0.2.dist-info/WHEEL
hdfuse-1.0.2.dist-info/entry_points.txt
hdfuse-1.0.2.dist-info/top_level.txt
hdfuse-1.0.2.dist-info/RECORD
