Metadata-Version: 2.1
Name: hdfuse
Version: 1.0.2
Summary: hdfuse is a tool for quick inspection of HDF5 files
Home-page: https://github.com/dtasev/hdfuse5
Author: Dimitar Tasev
Author-email: dimtasev@gmail.com
License: UNKNOWN
Platform: UNKNOWN
Classifier: Programming Language :: Python :: 3.6
Classifier: Operating System :: Unix
Requires-Python: >=3.6
Requires-Dist: fusepy
Requires-Dist: h5py
